pytest_recorder/__init__.py
pytest_recorder/plugin.py
pytest_recorder/record_curl.py
pytest_recorder/record_ftp.py
pytest_recorder/record_http.py
pytest_recorder/record_time.py
pytest_recorder/record_type.py
pytest_recorder/record_verify_object.py
pytest_recorder/record_verify_screen.py
pytest_recorder-0.6.3.dist-info/METADATA
pytest_recorder-0.6.3.dist-info/WHEEL
pytest_recorder-0.6.3.dist-info/entry_points.txt
pytest_recorder-0.6.3.dist-info/RECORD
