Metadata-Version: 2.4
Name: pytest-recorder
Version: 0.6.3
Summary: Pytest plugin, meant to facilitate unit tests writing for tools consumming Web APIs.
License: MIT
Author: Chavithra Parana
Author-email: chavithra@gmail.com
Requires-Python: >=3.10,<4.0
Classifier: Framework :: Pytest
Classifier: License :: OSI Approved :: MIT License
Classifier: Programming Language :: Python :: 3
Classifier: Programming Language :: Python :: 3.10
Classifier: Programming Language :: Python :: 3.11
Classifier: Programming Language :: Python :: 3.12
Classifier: Programming Language :: Python :: 3.13
Classifier: Programming Language :: Python :: 3.14
Provides-Extra: curl
Requires-Dist: black (>=25.1.0,<26.0.0)
Requires-Dist: cryptography (>=46.0.2,<47.0.0)
Requires-Dist: curl-cffi (>=0.11.0) ; extra == "curl"
Requires-Dist: idna (>=3.7,<4.0)
Requires-Dist: mypy (>=1.17.0,<2.0.0)
Requires-Dist: pycurl (>=7.45.5) ; extra == "curl"
Requires-Dist: pylint (>=3.3.7,<4.0.0)
Requires-Dist: pytest (>=8.4.1)
Requires-Dist: pytest-mock (>=3.15.1,<4.0.0)
Requires-Dist: time-machine (>=2.16.0,<3.0.0)
Requires-Dist: vcrpy (>=7) ; platform_python_implementation == "CPython"
